msumastro/__init__.py
msumastro/conftest.py
msumastro/customlogger.py
msumastro/table_tree.py
msumastro/header_processing/__init__.py
msumastro/header_processing/astrometry.py
msumastro/header_processing/feder.py
msumastro/header_processing/fitskeyword.py
msumastro/header_processing/patchers.py
msumastro/header_processing/tests/__init__.py
msumastro/header_processing/tests/test_feder.py
msumastro/header_processing/tests/test_fitskeyword.py
msumastro/header_processing/tests/test_patchers.py
msumastro/scripts/__init__.py
msumastro/scripts/quick_add_keys_to_file.py
msumastro/scripts/run_astrometry.py
msumastro/scripts/run_patch.py
msumastro/scripts/run_standard_header_process.py
msumastro/scripts/run_triage.py
msumastro/scripts/script_helpers.py
msumastro/scripts/sort_files.py
msumastro/scripts/tests/__init__.py
msumastro/scripts/tests/test_scripts.py
msumastro/tests/__init__.py
msumastro/tests/data.py
msumastro/tests/test_image_grouper.py
msumastro/tests/data/aspen_trimmed.fit
msumastro/tests/data/biastest1.fit
msumastro/tests/data/biastest2.fit
msumastro/tests/data/biastest3.fit
msumastro/tests/data/biastest4.fit
msumastro/tests/data/biastest5.fit
msumastro/tests/data/celestron_nightscape_10100_astro_fx_v106.fit
msumastro/tests/data/darktest1.fit
msumastro/tests/data/darktest2.fit
msumastro/tests/data/darktest3.fit
msumastro/tests/data/darktest4.fit
msumastro/tests/data/darktest5.fit
msumastro/tests/data/flattest.fit
msumastro/tests/data/maximdl_5_21_header.fit
msumastro/tests/data/maximdl_5_23_header.fit
msumastro/tests/data/maximdl_6_16_header.fit
msumastro/tests/data/maximdl_6_18_header.fit
msumastro/tests/data/neon-on-dome-10-sec-high-res-though-scope.fit
msumastro/tests/data/uint16.fit
msumastro/tests/data/uint16_missing_filter.fit
msumastro/tests/data/uint16_no_pointing.fit
msumastro/tests/data/uint16_not_m101.fit
msumastro-1.2.7.dist-info/METADATA
msumastro-1.2.7.dist-info/WHEEL
msumastro-1.2.7.dist-info/entry_points.txt
msumastro-1.2.7.dist-info/top_level.txt
msumastro-1.2.7.dist-info/RECORD
