Metadata-Version: 2.1
Name: msumastro
Version: 1.2.7
Summary: Process FITS files
Home-page: http://github.com/mwcraig/msumastro
Author: Matt Craig
Author-email: mattwcraig@gmail.com
License: BSD 3-Clause
Classifier: Development Status :: 4 - Beta
Classifier: License :: OSI Approved :: BSD License
Classifier: Intended Audience :: Science/Research
Classifier: Topic :: Scientific/Engineering :: Astronomy
Requires-Python: >=3.7
Requires-Dist: astropy
Requires-Dist: ccdproc
Requires-Dist: numpy
Provides-Extra: docs
Requires-Dist: numpydoc; extra == "docs"
Requires-Dist: sphinx-argparse; extra == "docs"
Requires-Dist: sphinx-rtd-theme; extra == "docs"
Requires-Dist: sphinx-astropy; extra == "docs"
Provides-Extra: tests
Requires-Dist: pytest-astropy; extra == "tests"
